soulknight/__init__.py
soulknight/cursor.py
soulknight/engine.py
soulknight/graph.py
soulknight/main.py
soulknight/orc.png
soulknight/person.png
soulknight/skeleton.png
soulknight/sprites.py
soulknight/tmx.py
soulknight/maps/1.tsx
soulknight/maps/16.tsx
soulknight/maps/map1.tmx
soulknight/maps/map2.tmx
soulknight/maps/tiny-16-basic.png
soulknight/tiledtmxloader-3.1.0.115/doc/html/_static/comment-bright.png
soulknight/tiledtmxloader-3.1.0.115/doc/html/_static/comment-close.png
soulknight/tiledtmxloader-3.1.0.115/doc/html/_static/comment.png
soulknight/tiledtmxloader-3.1.0.115/doc/html/_static/down-pressed.png
soulknight/tiledtmxloader-3.1.0.115/doc/html/_static/down.png
soulknight/tiledtmxloader-3.1.0.115/doc/html/_static/file.png
soulknight/tiledtmxloader-3.1.0.115/doc/html/_static/minus.png
soulknight/tiledtmxloader-3.1.0.115/doc/html/_static/plus.png
soulknight/tiledtmxloader-3.1.0.115/doc/html/_static/up-pressed.png
soulknight/tiledtmxloader-3.1.0.115/doc/html/_static/up.png
soulknight/tiledtmxloader-3.1.0.115/examples/graphics/tiles/collision.png
soulknight/tiledtmxloader-3.1.0.115/examples/graphics/tiles/desert1.png
soulknight/tiledtmxloader-3.1.0.115/examples/graphics/tiles/desert2.png
soulknight/tiledtmxloader-3.1.0.115/examples/graphics/tiles/desert_x2.png
soulknight/tiledtmxloader-3.1.0.115/examples/graphics/tiles/desert_x3.png
soulknight/tiledtmxloader-3.1.0.115/examples/graphics/tiles/desert_x5.png
soulknight/tiledtmxloader-3.1.0.115/examples/graphics/tiles/tictactoe.png
soulknight/tiledtmxloader-3.1.0.115/examples/graphics/tiles/trans_woodland-desert.png
soulknight/tiledtmxloader-3.1.0.115/examples/graphics/tiles/tulimshar1.png
soulknight/tiledtmxloader-3.1.0.115/test/minix.png
soulknight/tiledtmxloader-3.1.0.115/test/watertileset3qb2tg0.png
soulknight/tiledtmxloader-3.1.0.115/test/mini2/mini2x.png
soulknight/tiledtmxloader-3.1.0.115/test/mini3/tileset/mini3x.png
soulknight/tiledtmxloader-3.1.0.115/test/mini4/tileset/graphics/mini4x.png
soulknight-1.3.dist-info/METADATA
soulknight-1.3.dist-info/WHEEL
soulknight-1.3.dist-info/entry_points.txt
soulknight-1.3.dist-info/top_level.txt
soulknight-1.3.dist-info/RECORD
