Metadata-Version: 2.1
Name: soulknight
Version: 1.3
Summary: The funniest joke in the world
Home-page: https://github.com/9kin/soul-knight
Author: 9kin
Author-email: UNKNOWN
License: MIT
Keywords: game for yandex lyceum
Platform: UNKNOWN
Classifier: Programming Language :: Python :: 3.7
Requires-Dist: tiledtmxloader
Requires-Dist: pygame
Requires-Dist: pygame-menu
